glaring_simulation/Glaring.py
glaring_simulation/__init__.py
glaring_simulation-0.1.3.dist-info/LICENSE
glaring_simulation-0.1.3.dist-info/METADATA
glaring_simulation-0.1.3.dist-info/WHEEL
glaring_simulation-0.1.3.dist-info/top_level.txt
glaring_simulation-0.1.3.dist-info/RECORD
