Metadata-Version: 2.1
Name: glaring-simulation
Version: 0.1.3
Summary: Augmentation methods: glaring
Home-page: https://github.com/thomle295/glaring_simulation
Author: ThomLe
Author-email: thomlestudy295@gmail.com
License: MIT
Platform: UNKNOWN
Classifier: License :: OSI Approved :: MIT License
Classifier: Programming Language :: Python :: 3
Classifier: Programming Language :: Python :: 3.7
Classifier: Programming Language :: Python :: 3.8
Requires-Dist: numpy
Requires-Dist: opencv-python
